{
    "background": "#1B2B34",
    "black": "#252525",
    "blue": "#40C4FF",
    "brightBlack": "#343D46",
    "brightBlue": "#6699CC",
    "brightCyan": "#5FB3B3",
    "brightGreen": "#99C794",
    "brightPurple": "#FF4081",
    "brightRed": "#EC5F67",
    "brightWhite": "#D8DEE9",
    "brightYellow": "#FAC863",
    "cursorColor": "#FFFFFF",
    "cyan": "#18FFFF",
    "foreground": "#A1B0B8",
    "green": "#C3D82C",
    "name": "Oceanic",
    "purple": "#C594C5",
    "red": "#FF5252",
    "selectionBackground": "#9cb0b9",
    "white": "#F5F5F5",
    "yellow": "#FFD740"
}